examples/__init__.py
examples/env_examples.py
examples/ex01-mskcc.py
examples/ex02-capra.py
examples/ex03-custom.py
prostate_nomograms/__init__.py
prostate_nomograms/enum.py
prostate_nomograms/capra/__init__.py
prostate_nomograms/capra/capra.py
prostate_nomograms/capra/base/__init__.py
prostate_nomograms/capra/base/logistic_regression.py
prostate_nomograms/capra/base/survival_regression.py
prostate_nomograms/custom/__init__.py
prostate_nomograms/custom/custom.py
prostate_nomograms/custom/base/__init__.py
prostate_nomograms/custom/base/logistic_regression.py
prostate_nomograms/custom/base/survival_regression.py
prostate_nomograms/mskcc/__init__.py
prostate_nomograms/mskcc/pre_radical_prostatectomy_nomogram.py
prostate_nomograms/mskcc/base/__init__.py
prostate_nomograms/mskcc/base/logistic_regression.py
prostate_nomograms/mskcc/base/model.py
prostate_nomograms/mskcc/base/survival_regression.py
prostate_nomograms/mskcc/base/web_table_scraper.py
prostate_nomograms-0.0.9.dist-info/LICENSE
prostate_nomograms-0.0.9.dist-info/METADATA
prostate_nomograms-0.0.9.dist-info/WHEEL
prostate_nomograms-0.0.9.dist-info/top_level.txt
prostate_nomograms-0.0.9.dist-info/RECORD
