Metadata-Version: 2.1
Name: prostate-nomograms
Version: 0.0.9
Summary: Prediction tools based on existing prostate cancer nomograms.
Home-page: https://github.com/MaxenceLarose/prostate-nomograms
Author: Maxence Larose
Author-email: maxence.larose.1@ulaval.ca
License: Apache License 2.0
Keywords: cancer medical nomogram prediction prostate python3
Classifier: Programming Language :: Python :: 3
Classifier: License :: OSI Approved :: Apache Software License
Classifier: Operating System :: OS Independent
Requires-Python: >=3.7
License-File: LICENSE
Requires-Dist: lxml
Requires-Dist: numpy
Requires-Dist: openpyxl
Requires-Dist: pandas
Requires-Dist: requests
Requires-Dist: scikit-learn
Requires-Dist: scikit-survival
Requires-Dist: scipy
